cpu_scheduling/__init__.py
cpu_scheduling/fcfs.py
cpu_scheduling/priority.py
cpu_scheduling/round_robbin.py
cpu_scheduling/sjf.py
cpu_scheduling/srtf.py
cpu_scheduling_tk09-0.1.0.dist-info/METADATA
cpu_scheduling_tk09-0.1.0.dist-info/WHEEL
cpu_scheduling_tk09-0.1.0.dist-info/top_level.txt
cpu_scheduling_tk09-0.1.0.dist-info/RECORD
